[{"ts":1659271293,"title":"江明宗新增了 3 張相片。","text":"白天跟著 江國銘  、 江品璁  東奔西跑，看得出來三江垂頭喪氣的樣子嗎？旁邊三個小鬼還一直咬著棒棒糖笑我們！\n\n#買不起厝\n#北中西區台南市議員參選人江明宗","external":[],"images":[{"file":"2022-07/483858153743604.jpg","title":"手機上傳","description":""},{"file":"2022-07/483858197076933.jpg","title":"手機上傳","description":""},{"file":"2022-07/483858233743596.jpg","title":"手機上傳","description":""}]},{"ts":1659270280,"title":"江明宗新增了 1 張相片。","text":"政治獻金專戶第 3 個月收到 42 位捐款人共 60100 捐款\n\n我的政治獻金專戶自 4/27 啟用以來已經滿 3 個月，收到共 60100 捐款，來自 42 位捐款人，感謝支持！\n\n#北中西區台南市議員參選人江明宗\n#小額捐款支持明宗 https://kiang.oen.tw","external":[],"images":[{"file":"2022-07/483847987077954.jpg","title":"相片","description":"政治獻金專戶第 3 個月收到 42 位捐款人共 60100 捐款\n\n我的政治獻金專戶自 4/27 啟用以來已經滿 3 個月，收到共 60100 捐款，來自 42 位捐款人，感謝支持！\n\n#北中西區台南市議員參選人江明宗\n#小額捐款支持明宗 https://kiang.oen.tw"}]},{"ts":1659256962,"title":"江明宗新增了 1 張相片。","text":"選舉黃頁開發者江明宗回應陳明通聲明\n\n陳明通先生聲明提及選舉黃頁網站刊載的許明財學歷資料，依據系統記錄最早是在 2014-10-02 22:34:27 由匿名網友提供， 2014 大選日期是 2014-11-29 ，從時間的差異可以看出這筆資料並非取自選舉公報，提供的網友很可能是直接參考了國民黨網站。\n\n選舉黃頁不同於「選舉公報」，因為除了匯入中選會公佈的資料，選舉黃頁亦開放網友匿名編輯，在志工協助審核後資料就會上線，並沒有選舉公報這樣嚴謹的審查過程，自然也不該把選舉黃頁的資料視為「選舉公報」。\n\n我建置選舉黃頁網站的目的是希望更多朋友願意在選舉前一起做些功課，促進台灣政治文化的提昇；這次事件出現的資料差異也說明了中選會應該更積極做好開放資料工作，讓民間可以取得完整的選舉公報資料，這樣一來在進行選舉相關研究時就可以維持資訊的正確與一致性。\n\n選舉黃頁是本人「自我發揮」的成果，也藉此提醒未來進行選舉研究的朋友留意，使用資料記得多方查證，我沒辦法拯救任何人的學位 ;)\n\n選舉黃頁 - https://elections.olc.tw/\n\n#北中西區台南市議員參選人江明宗","external":[],"images":[{"file":"2022-07/483743033755116.jpg","title":"相片","description":"選舉黃頁開發者江明宗回應陳明通聲明\n\n陳明通先生聲明提及選舉黃頁網站刊載的許明財學歷資料，依據系統記錄最早是在 2014-10-02 22:34:27 由匿名網友提供， 2014 大選日期是 2014-11-29 ，從時間的差異可以看出這筆資料並非取自選舉公報，提供的網友很可能是直接參考了國民黨網站。\n\n選舉黃頁不同於「選舉公報」，因為除了匯入中選會公佈的資料，選舉黃頁亦開放網友匿名編輯，在志工協助審核後資料就會上線，並沒有選舉公報這樣嚴謹的審查過程，自然也不該把選舉黃頁的資料視為「選舉公報」。\n\n我建置選舉黃頁網站的目的是希望更多朋友願意在選舉前一起做些功課，促進台灣政治文化的提昇；這次事件出現的資料差異也說明了中選會應該更積極做好開放資料工作，讓民間可以取得完整的選舉公報資料，這樣一來在進行選舉相關研究時就可以維持資訊的正確與一致性。\n\n選舉黃頁是本人「自我發揮」的成果，也藉此提醒未來進行選舉研究的朋友留意，使用資料記得多方查證，我沒辦法拯救任何人的學位 ;)\n\n選舉黃頁 - https://elections.olc.tw/\n\n#北中西區台南市議員參選人江明宗"}]},{"ts":1659240077,"title":"江明宗新增了 3 張相片。","text":"三江下週街講行程出爐， 8/2 國銘、 8/4 明宗會去台北參加錄影活動\n\n早上 07:00-08:00 \n8/1 品璁 良美百貨\n8/2 明宗 中西區忠義路二段、府前路交叉口\n8/3 國銘 仁德區中山路822號\n8/4 品璁 中正路、中正北路（鹽行）\n8/5 國銘 鮮自然歸仁中山門市_ 歸仁區中山路一段466號\n\n下午 5:00-6:00\n8/1 明宗 北區公園北路、西門路交叉口\n8/2 品璁 中山南路、東橋七路交叉口\n8/3 明宗 中西區西門路、府前路交叉口\n8/4 國銘 仁德中油民安站_ 仁德區民安路一段325號 對面的人行道\n8/5 品璁 公園路、永大路二段交叉口\n\n江國銘 江品璁 #北中西區台南市議員參選人江明宗","external":[],"images":[{"file":"2022-07/483616643767755.jpg","title":"手機上傳","description":""},{"file":"2022-07/483616700434416.jpg","title":"手機上傳","description":""},{"file":"2022-07/483616740434412.jpg","title":"手機上傳","description":""}]},{"ts":1659225780,"title":"江明宗新增了 1 張相片。","text":"今天是走唱行程\n\n#北中西區台南市議員參選人江明宗","external":[],"images":[{"file":"2022-07/483505920445494.jpg","title":"手機上傳","description":"今天是走唱行程\n\n#北中西區台南市議員參選人江明宗"}]},{"ts":1659186332,"title":"江明宗新增了 1 張相片。","text":"拿到一碗泡麵，聽到一句『請明宗自我發揮一下』，可是我真的吃不下了，合照可以嗎？","external":[],"images":[{"file":"2022-07/483163047146448.jpg","title":"手機上傳","description":"拿到一碗泡麵，聽到一句『請明宗自我發揮一下』，可是我真的吃不下了，合照可以嗎？"}]},{"ts":1659180220,"title":"江明宗新增了 4 張相片。","text":"下午跟 洪岳銘 一起參與 台南社區大學 舉辦的公民肥皂箱活動，在活動中跟在場的民眾訴說自己參選政見；我所探討的 #步行城市 也是許多參選人討論的焦點，台南在交通議題真的有很大努力空間，希望 台灣民眾黨 的我們可以進入議會大力推動改革！\n\n也感謝台南社大用心安排這個活動，期待未來有更多機會切磋政見與議題，確實改變台南的選舉文化。\n\n#北中西區台南市議員參選人江明宗 \n#小額捐款支持明宗 https://kiang.oen.tw","external":[],"images":[{"file":"2022-07/483105313818888.jpg","title":"手機上傳","description":""},{"file":"2022-07/483105350485551.jpg","title":"手機上傳","description":""},{"file":"2022-07/483105387152214.jpg","title":"手機上傳","description":""},{"file":"2022-07/483105417152211.jpg","title":"手機上傳","description":""}]},{"ts":1659159461,"title":"江明宗分享了 1 則貼文。","text":"等一下在文化中心，我跟 @[100077302973805:2048:洪岳銘] 會站上公民肥皂箱，談我們的政見也回應公民提問，歡迎 3 點來跟我們交流！","external":[{"url":"","name":""}],"images":[]},{"ts":1659148007,"title":"江明宗新增了 4 張相片。","text":"早上參與的是 台南市導覽協會 舉辦的走讀活動，從西羅殿開始走訪五條港遺跡，透過老師的介紹得知一些地景設計的緣由，內容相當豐富。\n\n傳統的街屋大多是 4-5 米寬，裡面非常深，主要是因為當時能夠買到的木材普遍這個長度，許多老房子保留了這樣的風格；這些老房子大多只留下輪廓，透過老師的講解認識背後的故事。\n\n#北中西區台南市議員參選人江明宗","external":[],"images":[{"file":"2022-07/482837897178963.jpg","title":"手機上傳","description":""},{"file":"2022-07/482837933845626.jpg","title":"手機上傳","description":""},{"file":"2022-07/482837960512290.jpg","title":"手機上傳","description":""},{"file":"2022-07/482837990512287.jpg","title":"手機上傳","description":""}]},{"ts":1659140345,"title":"江明宗新增了 1 張相片。","text":"早安，等一下要去參加走讀活動，先來個蛋餅補充體力\n\n我已經習慣不加調味料，因為台南的空氣中有糖 (誤)\n\n#北中西區台南市議員參選人江明宗","external":[],"images":[{"file":"2022-07/482781113851308.jpg","title":"手機上傳","description":"早安，等一下要去參加走讀活動，先來個蛋餅補充體力\n\n我已經習慣不加調味料，因為台南的空氣中有糖 (誤)\n\n#北中西區台南市議員參選人江明宗"}]},{"ts":1659086809,"title":"江明宗新增了 4 張相片。","text":"下午受邀參與 JETS 嘉年華的開幕，我跟 蔡宛秦。政治 x 三寶媽 、 江國銘 、  江品璁 、 台南政治實習菜鳥 一起來到現場參與。\n\nJETS 嘉年華是美式展覽型遊樂園，即日起到 10/10 前提供大家購票遊玩，計有 18 項設施，今天就有許多民眾來到現場玩，暑假有空不妨帶孩子來玩！\n\n#北中西區台南市議員參選人江明宗","external":[],"images":[{"file":"2022-07/482310867231666.jpg","title":"手機上傳","description":""},{"file":"2022-07/482310903898329.jpg","title":"手機上傳","description":""},{"file":"2022-07/482310950564991.jpg","title":"手機上傳","description":""},{"file":"2022-07/482310990564987.jpg","title":"手機上傳","description":""}]},{"ts":1659053910,"title":"江明宗新增了 4 張相片。","text":"早上 江國銘 的街講來到仁德，我跟 江品璁 、台南政治實習菜鳥 一起站在街頭，持續呼喊我們的參政理念。林志堅論文案的背後是現有政治的文化縮影，花費太多社會成本去維持表面功夫， 台灣民眾黨 的我們希望務實解決眼前問題，期待年底選舉可以支持我們！\n\n#北中西區台南市議員參選人江明宗","external":[],"images":[{"file":"2022-07/482049530591133.jpg","title":"手機上傳","description":""},{"file":"2022-07/482049570591129.jpg","title":"手機上傳","description":""},{"file":"2022-07/482049607257792.jpg","title":"手機上傳","description":""},{"file":"2022-07/482049647257788.jpg","title":"手機上傳","description":""}]},{"ts":1659045026,"title":"江明宗更新了他的近況。","text":"日本京都府 257 萬人口， 1-6 月交通事故身亡 19 人；台南 188 萬人口， 1-5 月交通事故身亡 132 人","external":[],"images":[]},{"ts":1659014379,"title":"江明宗新增了 1 張相片。","text":"北區發生地震？為什麼我沒感覺…\n\n是說這個震央很罕見的感覺","external":[],"images":[{"file":"2022-07/481721980623888.jpg","title":"手機上傳","description":"北區發生地震？為什麼我沒感覺…\n\n是說這個震央很罕見的感覺"}]},{"ts":1659005868,"title":"江明宗新增了 1 張相片。","text":"#仁德歸仁關廟龍崎 市議員要投誰？\n我在理智上、情感上都是推薦、唯一支持\n三江之一的 江國銘 \n\n可是有人提到 #非綠不投 只投綠色的市議員\n要問投誰比較好？\n我們沒有政黨之間的隔閡\n如果在仁德歸仁關廟龍崎區 只投綠色的話 在此推薦\n持續為特色公園發聲的 郭鴻儀-議員日常 \n\n#北中西區台南市議員參選人江明宗","external":[],"images":[{"file":"2022-07/481639800632106.jpg","title":"手機上傳","description":"#仁德歸仁關廟龍崎 市議員要投誰？\n我在理智上、情感上都是推薦、唯一支持\n三江之一的 @[100045208796770:2048:江國銘] \n\n可是有人提到 #非綠不投 只投綠色的市議員\n要問投誰比較好？\n我們沒有政黨之間的隔閡\n如果在仁德歸仁關廟龍崎區 只投綠色的話 在此推薦\n持續為特色公園發聲的 @[100039496131944:2048:郭鴻儀-議員日常] \n\n#北中西區台南市議員參選人江明宗"}]},{"ts":1659004443,"title":"江明宗新增了 4 張相片。","text":"下午 江國銘 在仁德街講，我跟 江品璁 、 台南政治實習菜鳥 一起站在街頭，訴說參政理念。台南與台灣的政治傾向財團嚴重，導致許多公共政策頭痛醫頭，像少子化的問題，除了補助外更需要處理少子化、高房價問題，希望年底選舉大家可以支持 台灣民眾黨 的我們，進入議會改變台南年輕人的困境！\n\n#北中西區台南市議員參選人江明宗","external":[],"images":[{"file":"2022-07/481627437300009.jpg","title":"手機上傳","description":""},{"file":"2022-07/481627523966667.jpg","title":"手機上傳","description":""},{"file":"2022-07/481627563966663.jpg","title":"手機上傳","description":""},{"file":"2022-07/481627597299993.jpg","title":"手機上傳","description":""}]},{"ts":1658996769,"title":"江明宗新增了 2 張相片。","text":"台南的每十萬人口死傷人數長期都是全國最高，雖然對比去年到 5 月減少 7.7% 事故死亡，但 132 個生命消逝還是相當驚人\n\n#步行城市科技監督\n#北中西區台南市議員參選人江明宗","external":[],"images":[{"file":"2022-07/481568133972606.jpg","title":"相片","description":""},{"file":"2022-07/481568140639272.jpg","title":"相片","description":""}]},{"ts":1658971836,"title":"江明宗新增了 4 張相片。","text":"早上來到北區街講，感謝 江國銘 、 江品璁 、 台南政治實習菜鳥 到場支援，持續在街頭宣揚 #步行城市 理念。日本京都在疫情前每年有 3000 萬觀光客，步行體驗讓每個到訪朋友留下深刻印象，自詡為台灣京都的台南，應該要更積極的跟上腳步，請大家年底選舉支持 台灣民眾黨 的我們進入議會！\n\n#北中西區台南市議員參選人江明宗 \n#小額捐款支持明宗 https://kiang.oen.tw","external":[],"images":[{"file":"2022-07/481385310657555.jpg","title":"手機上傳","description":""},{"file":"2022-07/481385347324218.jpg","title":"手機上傳","description":""},{"file":"2022-07/481385383990881.jpg","title":"手機上傳","description":""},{"file":"2022-07/481385410657545.jpg","title":"手機上傳","description":""}]},{"ts":1658918060,"title":"江明宗新增了 1 張相片。","text":"下午的街講來到北區，感謝 江國銘 、 江品璁 與 台南政治實習菜鳥 與志工來到現場支援，我繼續宣傳 #步行城市 的理念。府城歷史街區應該成為台南或甚至台灣的步行典範，因為這裡有豐富的歷史街景，也有引以為傲的慢活， 台灣民眾黨 的我們進入議會一定會努力推進台南的步行環境發展，請台南的朋友支持！\n\n#北中西區台南市議員參選人江明宗\n#小額捐款支持明宗 https://kiang.oen.tw","external":[],"images":[{"file":"2022-07/480917297371023.jpg","title":"手機上傳","description":"下午的街講來到北區，感謝 @[100045208796770:2048:江國銘] 、 @[100065672431935:2048:江品璁] 與 台南政治實習菜鳥 與志工來到現場支援，我繼續宣傳 #步行城市 的理念。府城歷史街區應該成為台南或甚至台灣的步行典範，因為這裡有豐富的歷史街景，也有引以為傲的慢活， @[100044175652155:2048:台灣民眾黨] 的我們進入議會一定會努力推進台南的步行環境發展，請台南的朋友支持！\n\n#北中西區台南市議員參選人江明宗\n#小額捐款支持明宗 https://kiang.oen.tw"}]},{"ts":1658887051,"title":"江明宗更新了他的近況。","text":"北區、東區都有朋友回報停電，這次不知道該那個動物擔？","external":[],"images":[]},{"ts":1658882085,"title":"江明宗新增了 4 張相片。","text":"早上 江品璁 在永康街講，我跟 江國銘 、 台南政治實習菜鳥 與志工們一起到場支援，持續宣揚我們的政治理念。現有政治在財團影響下盤根錯節，需要更多 台灣民眾黨 這樣沒有包袱的我們進入議會，讓政府真的能夠重視民眾心聲，希望大家年底選舉支持！\n\n#北中西區台南市議員參選人江明宗","external":[],"images":[{"file":"2022-07/480642864065133.jpg","title":"手機上傳","description":""},{"file":"2022-07/480642887398464.jpg","title":"手機上傳","description":""},{"file":"2022-07/480642924065127.jpg","title":"手機上傳","description":""},{"file":"2022-07/480642950731791.jpg","title":"手機上傳","description":""}]},{"ts":1658831414,"title":"江明宗新增了 4 張相片。","text":"下午 江品璁 在永康的街講，我跟 江國銘 、 台南政治實習菜鳥 一起參與，繼續在街頭宣傳我們的參政理念。眼前街上可以看到的廣告，最多是建商，其次就是各個參選人，不過 台灣民眾黨 的 我們沒有這樣的財力，所以一步一腳印的在街頭爭取支持，期待大家年底選舉惠賜一票！\n\n#北中西區台南市議員參選人江明宗","external":[],"images":[{"file":"2022-07/480206994108720.jpg","title":"手機上傳","description":""},{"file":"2022-07/480207030775383.jpg","title":"手機上傳","description":""},{"file":"2022-07/480207494108670.jpg","title":"手機上傳","description":""},{"file":"2022-07/480207540775332.jpg","title":"手機上傳","description":""}]},{"ts":1658795786,"title":"江明宗新增了 4 張相片。","text":"早上在歸仁參與 江國銘  的街講，我跟 江品璁  、 台南政治實習菜鳥  一起在街口宣傳參政理念。 我們期待這次可以來一場乾淨的選舉，不綁樁腳、不抹黑也不花大錢，用一步一腳印的方式爭取大家支持，希望更多朋友可以在年底把選票交給 台灣民眾黨  的我們！\n\n#北中西區台南市議員參選人江明宗","external":[],"images":[{"file":"2022-07/479933310802755.jpg","title":"手機上傳","description":""},{"file":"2022-07/479933344136085.jpg","title":"手機上傳","description":""},{"file":"2022-07/479933374136082.jpg","title":"手機上傳","description":""},{"file":"2022-07/479933400802746.jpg","title":"手機上傳","description":""}]},{"ts":1658757596,"title":"江明宗新增了 1 張相片。","text":"#信賴台灣\n#民眾香挺\n#桃園有伶\n\n賴香伶 、 江國銘 、 江品璁 \n\n#北中西區台南市議員參選人江明宗","external":[],"images":[{"file":"2022-07/479548524174567.jpg","title":"手機上傳","description":"#信賴台灣\n#民眾香挺\n#桃園有伶\n\n@[100046959711590:2048:賴香伶] 、 @[100045208796770:2048:江國銘] 、 @[100065672431935:2048:江品璁] \n\n#北中西區台南市議員參選人江明宗"}]},{"ts":1658754608,"title":"江明宗新增了 1 張相片。","text":"一個網友傳來訊息聊到這個新聞，雖然發生在基隆，但對於兩個女兒的爸爸來說，真的會害怕自己有一天也需要面對這個情況；我也是鼓勵孩子自己走路上學的爸爸，同時我持續追蹤的資料中台南一直都是交通事故死傷對比人口最高的城市，有時候在孩子走出門的同時也的確帶著些許的擔心，還是會忍不住偷偷跟著幾次，確定孩子安全走進學校才離開。\n\n在民眾檢舉違規被限縮的情況發生後，其實我也不知道究竟還要多少生命在道路上消逝才能再次推進新共識；希望這次參選的 #步行城市 理念真的有機會落實，讓孩子真的可以好好的往返家裡與學校之間，讓家長們不需要每天接送也可以確保孩子有條安全回家的路！\n\n希望陳妹妹一路好走 R.I.P.\n\n#北中西區台南市議員參選人江明宗","external":[],"images":[{"file":"2022-07/479505544178865.jpg","title":"相片","description":"一個網友傳來訊息聊到這個新聞，雖然發生在基隆，但對於兩個女兒的爸爸來說，真的會害怕自己有一天也需要面對這個情況；我也是鼓勵孩子自己走路上學的爸爸，同時我持續追蹤的資料中台南一直都是交通事故死傷對比人口最高的城市，有時候在孩子走出門的同時也的確帶著些許的擔心，還是會忍不住偷偷跟著幾次，確定孩子安全走進學校才離開。\n\n在民眾檢舉違規被限縮的情況發生後，其實我也不知道究竟還要多少生命在道路上消逝才能再次推進新共識；希望這次參選的 #步行城市 理念真的有機會落實，讓孩子真的可以好好的往返家裡與學校之間，讓家長們不需要每天接送也可以確保孩子有條安全回家的路！\n\n希望陳妹妹一路好走 R.I.P.\n\n#北中西區台南市議員參選人江明宗"}]},{"ts":1658751174,"title":"江明宗新增了 1 張相片。","text":"我的面紙已經發光了，今天好不容易等到 10 箱面紙寄來，開開心心的打開來看，才發現居然不是我的…\n\n江品璁 來幫忙的時候一起多開了幾箱，確認都是錯的，但也熊熊發現，原來這些面紙的主人是品璁過去評論過的 南投縣議員 葉仁創  ，當時還在網路 \"互動\" 過，不過我們還是乖乖請廠商來收回去。\n\n慘的是，我的面紙還是不知道什麼時候寄到，只能繼續等待了…\n\n#北中西區台南市議員參選人江明宗","external":[],"images":[{"file":"2022-07/479480527514700.jpg","title":"手機上傳","description":"我的面紙已經發光了，今天好不容易等到 10 箱面紙寄來，開開心心的打開來看，才發現居然不是我的…\n\n@[100065672431935:2048:江品璁] 來幫忙的時候一起多開了幾箱，確認都是錯的，但也熊熊發現，原來這些面紙的主人是品璁過去評論過的 @[100063724689189:2048:南投縣議員 葉仁創]  ，當時還在網路 \"互動\" 過，不過我們還是乖乖請廠商來收回去。\n\n慘的是，我的面紙還是不知道什麼時候寄到，只能繼續等待了…\n\n#北中西區台南市議員參選人江明宗"}]},{"ts":1658744489,"title":"江明宗新增了 3 張相片。","text":"下午是 江國銘 街講，我跟 江品璁 、 台南政治實習菜鳥 一起在現場支援，持續宣揚我們參政的理念。政治工作其實存在許多專業幕僚，只是聲音不容易獲得重視， 台灣民眾黨 的我們會以理性、務實、科學的精神去發揮政治專業的價值，拜託大家年底選舉支持！\n\n#北中西區台南市議員參選人江明宗","external":[],"images":[{"file":"2022-07/479423057520447.jpg","title":"手機上傳","description":""},{"file":"2022-07/479423100853776.jpg","title":"手機上傳","description":""},{"file":"2022-07/479423134187106.jpg","title":"手機上傳","description":""}]},{"ts":1658730032,"title":"江明宗新增了 1 張相片。","text":"上週孩子暑期輔導的班上又傳出同學確診，除了學校停課，在家裡觀察期間並沒有發現任何症狀，昨天晚上進行快篩的結果一家四口都還是陰性；希望疫情打亂行程的生活能夠盡快過去，也還是再次提醒大家疫苗打好打滿，讓防疫工作可以有效落實！\n\n#已經數不清幾次陰性\n#北中西區台南市議員參選人江明宗","external":[],"images":[{"file":"2022-07/479301320865954.jpg","title":"手機上傳","description":"上週孩子暑期輔導的班上又傳出同學確診，除了學校停課，在家裡觀察期間並沒有發現任何症狀，昨天晚上進行快篩的結果一家四口都還是陰性；希望疫情打亂行程的生活能夠盡快過去，也還是再次提醒大家疫苗打好打滿，讓防疫工作可以有效落實！\n\n#已經數不清幾次陰性\n#北中西區台南市議員參選人江明宗"}]},{"ts":1658714977,"title":"江明宗新增了 4 張相片。","text":"早上在北區進行街講，感謝 江國銘 、 江品璁 、 台南政治實習菜鳥 的支援，熱情的志工還特別上班時繞過來送飲料。 #步行城市 仍然是今天街講的核心，無論是否計劃生孩子，這個社會的持續發展仍然需要穩固的親子友善環境，步行空間是這個環境的基礎，希望更多朋友支持 台灣民眾黨 的我們，進入市議會讓步行城市的願景能夠實現！\n\n#北中西區台南市議員參選人江明宗\n#小額捐款支持明宗 https://kiang.oen.tw","external":[],"images":[{"file":"2022-07/479194910876595.jpg","title":"手機上傳","description":""},{"file":"2022-07/479194950876591.jpg","title":"手機上傳","description":""},{"file":"2022-07/479194990876587.jpg","title":"手機上傳","description":""},{"file":"2022-07/479195024209917.jpg","title":"手機上傳","description":""}]},{"ts":1658673510,"title":"江明宗分享了 1 則貼文。","text":"明天開始連續 4 天，萬安演習會在各地進行\n* 北部：7/25（一）13:30~14:00\n* 中部：7/26（二）13:30~14:00\n* 南部：7/27（三） 13:30~14:00\n* 東部＋離島：7/28（四）13:30~14:00\n\n台北已經率先提出要在演習過程實際使用防空避難處所，希望更多縣市跟進，讓民眾真的可以檢驗這些地方的現況，避免真的需要時才發現問題！","external":[{"url":"","name":""}],"images":[]},{"ts":1658647093,"title":"江明宗新增了 3 張相片。","text":"三江街講下週行程出爐，有空的朋友歡迎一起參與！ 江國銘  江品璁 \n\n早上\n7/25 明宗 08:00-09:00 北區 北安路、公園路交叉口\n7/26 國銘 07:00-08:00 86橋下 關廟往歸仁方向\n7/27 品璁 07:00-08:00 永康良美百貨 (金三角)\n7/28 明宗 08:00-09:00 北區 和緯路、西門路交叉口\n7/29 國銘 07:00-08:00 仁德 同喬眼鏡\n\n下午05:00-06:00\n7/25 國銘 仁德中山路 義林路交叉口 7-11林頂門市\n7/26 品璁 永大路二段、公園路交叉口\n7/27 明宗 文成三路、文賢路交叉口\n7/28 國銘 7-11常興門市 對面路口\n7/29 品璁 中山南路、東橋七路\n\n#北中西區台南市議員參選人江明宗","external":[],"images":[{"file":"2022-07/478626717600081.jpg","title":"手機上傳","description":""},{"file":"2022-07/478626754266744.jpg","title":"手機上傳","description":""},{"file":"2022-07/478626800933406.jpg","title":"手機上傳","description":""}]},{"ts":1658585731,"title":"江明宗新增了 1 張相片。","text":"美國紐約自 1996 開始執行一個綠街道(Greenstreets)計畫，試著把使用率較低的街道轉換為綠空間， Corona Plaza 就是超過 2500 個專案之一，改造前路邊停滿車輛，改造後變成人行廣場，讓更多人願意在街上駐留，廣場也吸引許多活動在這裡舉辦，帶動鄰近區域的發展。\n\n#步行城市 的理念也是希望透過道路空間的檢討來產生更多步行空間，步行空間擴大後可以促成更多連結，不僅帶動商業發展，也能夠讓更多民眾好好享受台南充滿歷史味道的街景，期待更多朋友支持！\n\n#小額捐款支持明宗 https://kiang.oen.tw\n#北中西區台南市議員參選人江明宗","external":[],"images":[{"file":"2022-07/478154307647322.jpg","title":"相片","description":"美國紐約自 1996 開始執行一個綠街道(Greenstreets)計畫，試著把使用率較低的街道轉換為綠空間， Corona Plaza 就是超過 2500 個專案之一，改造前路邊停滿車輛，改造後變成人行廣場，讓更多人願意在街上駐留，廣場也吸引許多活動在這裡舉辦，帶動鄰近區域的發展。\n\n#步行城市 的理念也是希望透過道路空間的檢討來產生更多步行空間，步行空間擴大後可以促成更多連結，不僅帶動商業發展，也能夠讓更多民眾好好享受台南充滿歷史味道的街景，期待更多朋友支持！\n\n#小額捐款支持明宗 https://kiang.oen.tw\n#北中西區台南市議員參選人江明宗"}]},{"ts":1658553091,"title":"江明宗新增了 1 張相片。","text":"今天是大暑，已經快被融化，所以自動路過全家報到，來個圓滾滾冰淇淋消暑一下！\n\n#眾夏冰品大PK\n介紹當地冰品，也為自己消消暑一下吧！\n\n我來點名\n 黃珊珊 賴香伶 高虹安 洪岳銘 劉家榮律師 \n\n快來一起 #眾夏冰品大PK\n「任務解鎖後記得在點名別人喔～～」\n\n#北中西區台南市議員參選人江明宗\n#小額捐款支持明宗 https://kiang.oen.tw","external":[],"images":[{"file":"2022-07/477873114342108.jpg","title":"手機上傳","description":"今天是大暑，已經快被融化，所以自動路過全家報到，來個圓滾滾冰淇淋消暑一下！\n\n#眾夏冰品大PK\n介紹當地冰品，也為自己消消暑一下吧！\n\n我來點名\n @[100044528885416:2048:黃珊珊] @[100046959711590:2048:賴香伶] @[100044992518779:2048:高虹安] @[100077302973805:2048:洪岳銘] @[100069021670179:2048:劉家榮律師] \n\n快來一起 #眾夏冰品大PK\n「任務解鎖後記得在點名別人喔～～」\n\n#北中西區台南市議員參選人江明宗\n#小額捐款支持明宗 https://kiang.oen.tw"}]},{"ts":1658486539,"title":"江明宗新增了 4 張相片。","text":"下午在台南公園街講，感謝 江國銘 、 江品璁 與 台南政治實習菜鳥 到場支援，繼續對大家闡述 #步行城市 的理念。台南的歷史街區得天獨厚，有許多古蹟與老房子讓街景特別有看頭，獨缺一個友善的步行環境，希望大家年底選舉支持 台灣民眾黨 的我們，讓台南因為步行城市發光發熱！\n\n#小額捐款支持明宗 https://kiang.oen.tw\n#北中西區台南市議員參選人江明宗","external":[],"images":[{"file":"2022-07/477266137736139.jpg","title":"手機上傳","description":""},{"file":"2022-07/477266167736136.jpg","title":"手機上傳","description":""},{"file":"2022-07/477266221069464.jpg","title":"手機上傳","description":""},{"file":"2022-07/477266254402794.jpg","title":"手機上傳","description":""}]},{"ts":1658458462,"title":"江明宗新增了 3 張相片。","text":"【保障網路言論自由，請NCC重提數位中介服務法草案】記者會發言摘要\n\n草案第五條定義了七個大方向，除了 \"兒童及少年權益之保障\" 較有共識外，其他方向都有很大想像空間，以最近林智堅市長論文案為例，如果蔡英文總統要求以 \"人性尊嚴之保障\" 或 \"國家安全或國防等公共安全維持\" 為由要求管制相關討論，這樣的情況大家能夠接受嗎？\n\n其次是草案第三條定義了大量的主管機關，每個主管機關都可以進行行政處分與申請法院禁制令，業者與民眾需要面對多頭馬車的情況；草案參考的歐盟與英國案例，每個國家都只會有單一主管機關發動程序，草案這樣便宜行事的作法讓人難以理解。\n\n雖然草案有提到法院程序，但第十八條卻開了一個後門，在法院裁定出現以前數位中介服務提供者對於行政機關的處分書 \"應予配合\" ，抗告期間也不會暫停處分，行政權被無止境的擴大！\n\n整個草案東拼西湊，歐盟或英國相關法規推行的精神在這個草案蕩然無存，因此我跟 邱臣遠 委員、 蔡壁如 委員與 楊寶楨 Christina 同聲呼籲 NCC 立即 #退回數位中介服務法草案 ！\n\n#北中西區台南市議員參選人江明宗","external":[],"images":[{"file":"2022-07/477056947757058.jpg","title":"手機上傳","description":""},{"file":"2022-07/477056981090388.jpg","title":"手機上傳","description":""},{"file":"2022-07/477057017757051.jpg","title":"手機上傳","description":""}]},{"ts":1658454431,"title":"江明宗新增了 1 張相片。","text":"下午還有街講行程，所以記者會後就直接準備搭車回台南，不過還是要再次呼籲 NCC #退回數位中介服務法草案 ，草案有太多缺乏共識的便宜行事！\n\n#北中西區台南市議員參選人江明宗","external":[],"images":[{"file":"2022-07/477026294426790.jpg","title":"手機上傳","description":"下午還有街講行程，所以記者會後就直接準備搭車回台南，不過還是要再次呼籲 NCC #退回數位中介服務法草案 ，草案有太多缺乏共識的便宜行事！\n\n#北中西區台南市議員參選人江明宗"}]},{"ts":1658442349,"title":"江明宗新增了 1 張相片。","text":"早安，今天 #漂向北方\n\n#北中西區台南市議員參選人江明宗","external":[],"images":[{"file":"2022-07/476940797768673.jpg","title":"手機上傳","description":"早安，今天 #漂向北方\n\n#北中西區台南市議員參選人江明宗"}]},{"ts":1658399132,"title":"江明宗新增了 4 張相片。","text":"下午 江品璁 在永康街講，我跟 江國銘 、 台南政治實習菜鳥 一起站在街頭，共同訴說這次的參選理念。眼前台灣與台南的政策明顯傾向財團，需要沒有包袱、 台灣民眾黨 的我們進入議會，真的為大家發聲，請大家年底選舉多多支持！\n\n#北中西區台南市議員參選人江明宗","external":[],"images":[{"file":"2022-07/476476891148397.jpg","title":"手機上傳","description":""},{"file":"2022-07/476476924481727.jpg","title":"手機上傳","description":""},{"file":"2022-07/476476961148390.jpg","title":"手機上傳","description":""},{"file":"2022-07/476476984481721.jpg","title":"手機上傳","description":""}]},{"ts":1658373434,"title":"江明宗新增了 1 張相片。","text":"台南豐富的文學底蘊隨處可見，像是這看不完的交通標語…\n\n#這就是警告疲勞\n#北中西區台南市議員參選人江明宗","external":[],"images":[{"file":"2022-07/476275534501866.jpg","title":"手機上傳","description":"台南豐富的文學底蘊隨處可見，像是這看不完的交通標語…\n\n#這就是警告疲勞\n#北中西區台南市議員參選人江明宗"}]},{"ts":1658366541,"title":"江明宗新增了 4 張相片。","text":"早上在中西區街講，感謝 台南政治實習菜鳥 支援， #步行城市 希望台南可以打造更友善的步行環境，既有的通學步道與友善騎樓政策執行多年，很多地方只有單點式的改善，希望大家年底支持 台灣民眾黨 的我們，讓台南的步行環境可以大步邁進！\n\n#小額捐款支持明宗 https://kiang.oen.tw\n#北中西區台南市議員參選人江明宗","external":[],"images":[{"file":"2022-07/476221071173979.jpg","title":"手機上傳","description":""},{"file":"2022-07/476221104507309.jpg","title":"手機上傳","description":""},{"file":"2022-07/476221141173972.jpg","title":"手機上傳","description":""},{"file":"2022-07/476221174507302.jpg","title":"手機上傳","description":""}]},{"ts":1658322899,"title":"江明宗新增了 4 張相片。","text":"下午 江國銘 來到仁德街講，我跟 江品璁 、 台南政治實習菜鳥 一起參與，我們在街頭探討少子化問題的根源，除了生育補助外更需要解決大環境的低薪問題， 台灣民眾黨 要在台南市議會組成黨團，用理性、科學、務實的精神形成政策，避免頭痛醫頭的作法一再發生！\n\n#北中西區台南市議員參選人江明宗","external":[],"images":[{"file":"2022-07/475783441217742.jpg","title":"手機上傳","description":""},{"file":"2022-07/475783474551072.jpg","title":"手機上傳","description":""},{"file":"2022-07/475783511217735.jpg","title":"手機上傳","description":""},{"file":"2022-07/475783544551065.jpg","title":"手機上傳","description":""}]},{"ts":1658296765,"title":"江明宗更新了他的近況。","text":"台灣言論自由是許多先進爭取的成果，不會只有特定政黨功勞，議員的工作是監督而非抱大腿！","external":[],"images":[]},{"ts":1658294937,"title":"江明宗新增了 1 張相片。","text":"中午跟 台南政治實習菜鳥 與志工約在 台灣民眾黨台南市黨部 特約餐廳吃飯，這裡的餐點都很美味，黨員出示證明還可以享有折扣，有空可以來試試！\n\n#北中西區台南市議員參選人江明宗","external":[],"images":[{"file":"2022-07/475558847906868.jpg","title":"手機上傳","description":"中午跟 台南政治實習菜鳥 與志工約在 @[100068850324817:2048:台灣民眾黨台南市黨部] 特約餐廳吃飯，這裡的餐點都很美味，黨員出示證明還可以享有折扣，有空可以來試試！\n\n#北中西區台南市議員參選人江明宗"}]},{"ts":1658276306,"title":"江明宗新增了 1 張相片。","text":"早上 江國銘 的街講來到歸仁高鐵橋下，我跟 台南政治實習菜鳥 一起參與，在街頭訴說眼前青年人面對的困境，為了買一間房子要 20-30 年不吃不喝，買了之後又要 20-30 年犧牲生活品質，這樣的環境需要 台灣民眾黨 的我們進入議會改變，懇請大家年底選舉支持！\n\n#北中西區台南市議員參選人江明宗","external":[],"images":[{"file":"2022-07/475411877921565.jpg","title":"手機上傳","description":"早上 @[100045208796770:2048:江國銘] 的街講來到歸仁高鐵橋下，我跟 台南政治實習菜鳥 一起參與，在街頭訴說眼前青年人面對的困境，為了買一間房子要 20-30 年不吃不喝，買了之後又要 20-30 年犧牲生活品質，這樣的環境需要 @[100044175652155:2048:台灣民眾黨] 的我們進入議會改變，懇請大家年底選舉支持！\n\n#北中西區台南市議員參選人江明宗"}]},{"ts":1658269505,"title":"江明宗新增了 1 張相片。","text":"早安，前往歸仁路上，今天開始騎乘機車不用配戴口罩，看起來大部分人都不太習慣\n\n#北中西區台南市議員參選人江明宗","external":[],"images":[{"file":"2022-07/475365177926235.jpg","title":"手機上傳","description":"早安，前往歸仁路上，今天開始騎乘機車不用配戴口罩，看起來大部分人都不太習慣\n\n#北中西區台南市議員參選人江明宗"}]},{"ts":1658238536,"title":"江明宗新增了 2 張相片。","text":"今天下午的街講有幾個小插曲，一個支持者突然騎機車停下表示要捐政治獻金，也有另外一位支持者送來飲料，非常感謝願意出錢出力幫忙的朋友，我會繼續努力爭取進入議會為大家服務的機會！\n\n#小額捐款支持明宗 https://kiang.oen.tw\n#北中西區台南市議員參選人江明宗","external":[],"images":[{"file":"2022-07/475060411290045.jpg","title":"手機上傳","description":""},{"file":"2022-07/475060464623373.jpg","title":"手機上傳","description":""}]},{"ts":1658229210,"title":"江明宗新增了 4 張相片。","text":"下午來到北區好市多街講， 江國銘  、 江品璁  與 台南政治實習菜鳥  跟志工們一起到場支援， #步行城市 的參選理念為的是提供孩子更友善的生活環境，讓孩子可以從家裡步行往返學校，漸進培養孩子獨立的能力。\n\n年底選舉請支持 台灣民眾黨  的我們！\n\n#小額捐款支持明宗 https://kiang.oen.tw\n#北中西區台南市議員參選人江明宗","external":[],"images":[{"file":"2022-07/474955807967172.jpg","title":"手機上傳","description":""},{"file":"2022-07/474955844633835.jpg","title":"手機上傳","description":""},{"file":"2022-07/474955871300499.jpg","title":"手機上傳","description":""},{"file":"2022-07/474955901300496.jpg","title":"手機上傳","description":""}]},{"ts":1658196495,"title":"江明宗新增了 4 張相片。","text":"早上來到美術館2館旁的路口街講，感謝 江國銘 、 台南政治實習菜鳥 與志工的參與，我仍然是不厭其煩的宣揚 #步行城市 理念，希望改善步行環境後讓更多人可以好好走在路上，減少車輛的使用來改善交通瓶頸，進而讓台南居高不下的交通事故死傷能夠有效降低，希望大家年底選舉支持 台灣民眾黨 的我們，一起進入議會把台南打造為步行城市！\n\n#小額捐款支持明宗 https://kiang.oen.tw\n#北中西區台南市議員參選人江明宗","external":[],"images":[{"file":"2022-07/474703807992372.jpg","title":"手機上傳","description":""},{"file":"2022-07/474703834659036.jpg","title":"手機上傳","description":""},{"file":"2022-07/474703861325700.jpg","title":"手機上傳","description":""},{"file":"2022-07/474703891325697.jpg","title":"手機上傳","description":""}]},{"ts":1658150191,"title":"江明宗更新了他的近況。","text":"在野黨批判執政黨，結果發聲的人被在野黨主動解職？ #張博洋 哭哭","external":[],"images":[]},{"ts":1658146006,"title":"江明宗新增了 4 張相片。","text":"下午 江品璁 的街講來到鹽行夜市，我跟 江國銘 、 台南政治實習菜鳥 一起宣揚參選理念，眼前許多公共政策跟財團利益掛勾，一般民眾的聲音被忽略無視，年底選舉請支持最在意民眾、 台灣民眾黨 的我們，讓我們在議會為你發聲！\n\n#北中西區台南市議員參選人江明宗","external":[],"images":[{"file":"2022-07/474238304705589.jpg","title":"手機上傳","description":""},{"file":"2022-07/474238348038918.jpg","title":"手機上傳","description":""},{"file":"2022-07/474238384705581.jpg","title":"手機上傳","description":""},{"file":"2022-07/474238421372244.jpg","title":"手機上傳","description":""}]},{"ts":1658103895,"title":"江明宗新增了 4 張相片。","text":"早上在仁德參與 江國銘 的街講， 台南政治實習菜鳥 一起支援，共同傳達不花大錢、不綁樁腳與不抹黑的參政理念， 柯文哲 主席說過，選舉花大錢是政治敗壞的開始，年底選舉請把選票投給 台灣民眾黨 的我們！\n\n#北中西區台南市議員參選人江明宗","external":[],"images":[{"file":"2022-07/473897071406379.jpg","title":"手機上傳","description":""},{"file":"2022-07/473897114739708.jpg","title":"手機上傳","description":""},{"file":"2022-07/473897161406370.jpg","title":"手機上傳","description":""},{"file":"2022-07/473897198073033.jpg","title":"手機上傳","description":""}]},{"ts":1658097528,"title":"江明宗新增了 1 張相片。","text":"早安，前往仁德的路上\n\n#北中西區台南市議員參選人江明宗","external":[],"images":[{"file":"2022-07/473853401410746.jpg","title":"手機上傳","description":"早安，前往仁德的路上\n\n#北中西區台南市議員參選人江明宗"}]},{"ts":1658060690,"title":"江明宗更新了他的近況。","text":"#郭再欽 續任民進黨中執委，不知道台南學甲爐渣案工業地部份什麼時候會著手處理？","external":[],"images":[]},{"ts":1657983871,"title":"江明宗新增了 3 張相片。","text":"下週街講行程出爐， 江國銘 、 江品璁 、 #江明宗 持續在街頭訴說參選理念，一步一腳印爭取大家的支持，街頭偶遇簡單點點頭都是很大的鼓勵！\n\n早上\n7/18 07:00-08:00 國銘 仁德區中山路822號\n7/19 08:00-09:00 明宗 中西區忠義路二段、府前路交叉口\n7/20 07:00-08:00 國銘 歸仁車之輪_ 歸仁區中山路三段666號\n7/21 08:00-09:00 明宗 北區西門路三段、成功路交叉口\n7/22 07:00-08:00 國銘 鮮自然歸仁中山門市_ 歸仁區中山路一段466號\n\n下午 05:00-06:00\n7/18 品璁 永康中正北路、中正路交叉口\n7/19 明宗 北區好市多路口\n7/20 國銘 仁德中油民安站_ 仁德區民安路一段325號 對面的人行道\n7/21 品璁 永康中山南路、東橋七路交叉口\n7/22 明宗 中西區公園南路、公園路交叉口\n\n#北中西區台南市議員參選人江明宗","external":[],"images":[{"file":"2022-07/472804241515662.jpg","title":"手機上傳","description":""},{"file":"2022-07/472804284848991.jpg","title":"手機上傳","description":""},{"file":"2022-07/472804321515654.jpg","title":"手機上傳","description":""}]},{"ts":1657936032,"title":"江明宗更新了他的近況。","text":"把話講清楚就不容易，刻意使用母語造成誤解反而得不償失","external":[],"images":[]},{"ts":1657932113,"title":"江明宗新增了 1 張相片。","text":"台灣民眾黨 王如意  、 張凱鈞 Ken Chang  、 勤文的思考事件簿  難得來到台南，早上帶大家一起去吃虱目魚， 江國銘 、 陳詩薇 市議員參選人/安南區 跟我分享了在地台南人的經驗，相約年底當選後再來深度台南旅遊！\n\n#北中西區台南市議員參選人江明宗","external":[],"images":[{"file":"2022-07/472350988227654.jpg","title":"手機上傳","description":"@[100079167634252:2048:台灣民眾黨 王如意]  、 @[100050337106527:2048:張凱鈞 Ken Chang]  、 @[100063454974134:2048:勤文的思考事件簿]  難得來到台南，早上帶大家一起去吃虱目魚， @[100045208796770:2048:江國銘] 、 @[100076077235082:2048:陳詩薇 市議員參選人/安南區] 跟我分享了在地台南人的經驗，相約年底當選後再來深度台南旅遊！\n\n#北中西區台南市議員參選人江明宗"}]},{"ts":1657903013,"title":"江明宗新增了 1 張相片。","text":"路過逛了一下，怎麼深夜還這麼多人！\n\n#北中西區台南市議員參選人江明宗","external":[],"images":[{"file":"2022-07/472112948251458.jpg","title":"手機上傳","description":"路過逛了一下，怎麼深夜還這麼多人！\n\n#北中西區台南市議員參選人江明宗"}]},{"ts":1657884445,"title":"江明宗新增了 4 張相片。","text":"下午參與 江國銘 在仁德的街講， 江品璁 、 台南政治實習菜鳥 也一起支援，三江一起在街口拜託大家支持，支持 台灣民眾黨 的我們進入議會，為更多年輕人發聲，把理性、務實、科學的力量帶進台南市議會！\n\n#北中西區台南市議員參選人江明宗","external":[],"images":[{"file":"2022-07/471911448271608.jpg","title":"手機上傳","description":""},{"file":"2022-07/471911538271599.jpg","title":"手機上傳","description":""},{"file":"2022-07/471911581604928.jpg","title":"手機上傳","description":""},{"file":"2022-07/471911664938253.jpg","title":"手機上傳","description":""}]},{"ts":1657870655,"title":"江明宗新增了 1 張相片。","text":"連續街講後喉嚨開始有點不舒服，所以還是快篩一下，應該是單純喉嚨不適\n\n#北中西區台南市議員參選人江明宗","external":[],"images":[{"file":"2022-07/471791904950229.jpg","title":"手機上傳","description":"連續街講後喉嚨開始有點不舒服，所以還是快篩一下，應該是單純喉嚨不適\n\n#北中西區台南市議員參選人江明宗"}]},{"ts":1657859279,"title":"江明宗新增了 1 張相片。","text":"台南廢棄物、廢土亂倒問題全國最嚴重，江明宗要求市府增加環保稽查人力\n\n北中西區台南市議員參選人江明宗透過資訊技術分析國土利用監測整合資訊網資料，台南市在近 2 年傾倒廢棄物、土的案件數全國最高， 110 年有 269 件、 111 年僅到 6 月為止就出現 233 件，台南儼然成為廢棄物之都！\n\n江明宗說，國土利用監測整合資訊網運用衛星影像觀測變異點技術成熟，傾倒廢棄物、土案件資訊往往可以第一時間發現，但隨後的稽查工作卻進度緩慢；江明宗說，政府公開資訊缺乏橫向連結，變異點的稽查結果與是否開罰、追蹤都是分開進行，資訊也未確實公開透明，讓民眾難以參與監督與追蹤。\n\n江明宗表示，黃偉哲市長上任以來傾倒廢棄物、土的案件逐年攀升，居高不下的廢棄物傾倒事件代表第一線稽查工作未能產生嚇阻效果，需要更多人力、物力投入遏止事件持續發生；江明宗認為，台南是許多農漁產品產地，傾倒廢棄物案件會引發食安疑慮，進而衝擊在地產業發展，江明宗呼籲黃偉哲市長重視台南的廢棄物處理問題！\n\n#小額捐款支持明宗 https://kiang.oen.tw\n#北中西區台南市議員參選人江明宗","external":[],"images":[{"file":"2022-07/471699468292806.jpg","title":"相片","description":"台南廢棄物、廢土亂倒問題全國最嚴重，江明宗要求市府增加環保稽查人力\n\n北中西區台南市議員參選人江明宗透過資訊技術分析國土利用監測整合資訊網資料，台南市在近 2 年傾倒廢棄物、土的案件數全國最高， 110 年有 269 件、 111 年僅到 6 月為止就出現 233 件，台南儼然成為廢棄物之都！\n\n江明宗說，國土利用監測整合資訊網運用衛星影像觀測變異點技術成熟，傾倒廢棄物、土案件資訊往往可以第一時間發現，但隨後的稽查工作卻進度緩慢；江明宗說，政府公開資訊缺乏橫向連結，變異點的稽查結果與是否開罰、追蹤都是分開進行，資訊也未確實公開透明，讓民眾難以參與監督與追蹤。\n\n江明宗表示，黃偉哲市長上任以來傾倒廢棄物、土的案件逐年攀升，居高不下的廢棄物傾倒事件代表第一線稽查工作未能產生嚇阻效果，需要更多人力、物力投入遏止事件持續發生；江明宗認為，台南是許多農漁產品產地，傾倒廢棄物案件會引發食安疑慮，進而衝擊在地產業發展，江明宗呼籲黃偉哲市長重視台南的廢棄物處理問題！\n\n#小額捐款支持明宗 https://kiang.oen.tw\n#北中西區台南市議員參選人江明宗"}]},{"ts":1657845998,"title":"江明宗新增了 4 張相片。","text":"早安！早上跟 江國銘  在北區街講，  台南政治實習菜鳥 與志工一起在現場支援， #步行城市 的參選理念是希望打造更友善的步行環境，無論台南居民或是來到台南觀光的朋友都可以好好走在街上，年底選舉請支持 台灣民眾黨  的我們，讓我們進入議會監督市政府，改善台南的步行環境！\n\n#小額捐款支持明宗 https://kiang.oen.tw\n#北中西區台南市議員參選人江明宗","external":[],"images":[{"file":"2022-07/471591061636980.jpg","title":"手機上傳","description":""},{"file":"2022-07/471591111636975.jpg","title":"手機上傳","description":""},{"file":"2022-07/471591154970304.jpg","title":"手機上傳","description":""},{"file":"2022-07/471591198303633.jpg","title":"手機上傳","description":""}]},{"ts":1657803937,"title":"江明宗新增了 4 張相片。","text":"下午在民生圓環旁街講， 江國銘 、 江品璁 、 黃國晏 與 台南政治實習菜鳥 到場支援， #步行城市 理念可以解決許多台南面臨的問題，讓通學步道真的可以通學、透過標線型人行道等政策擴大步行區域以及提供友善步行環境減少觀光客用車需求，期待年底選舉大家可以支持 台灣民眾黨 的我們走入議會，確實監督市府改善步行環境！\n\n#小額捐款支持明宗 https://kiang.oen.tw\n#北中西區台南市議員參選人江明宗","external":[],"images":[{"file":"2022-07/471205221675564.jpg","title":"手機上傳","description":""},{"file":"2022-07/471205265008893.jpg","title":"手機上傳","description":""},{"file":"2022-07/471205318342221.jpg","title":"手機上傳","description":""},{"file":"2022-07/471205351675551.jpg","title":"手機上傳","description":""}]},{"ts":1657760187,"title":"江明宗新增了 1 張相片。","text":"希望李部長珍惜生命，道歉就好\n\n#北中西區台南市議員參選人江明宗","external":[],"images":[{"file":"2022-07/470799431716143.jpg","title":"手機上傳","description":"希望李部長珍惜生命，道歉就好\n\n#北中西區台南市議員參選人江明宗"}]},{"ts":1657759711,"title":"江明宗更新了他的近況。","text":"早上大潮加地震，有民眾表示安平運河週邊河水溢流，請特別留意","external":[],"images":[]},{"ts":1657757500,"title":"江明宗新增了 4 張相片。","text":"早安！早上來到歸仁參與 江國銘 的街講， 台南政治實習菜鳥 與志工也一起支援，我們一起站在街頭宣揚參選理念，希望年底選舉大家可以支持，進入議會監督市政，改善台南的低薪、高房價與少子化問題！\n\n#北中西區台南市議員參選人江明宗","external":[],"images":[{"file":"2022-07/470780098384743.jpg","title":"手機上傳","description":""},{"file":"2022-07/470780128384740.jpg","title":"手機上傳","description":""},{"file":"2022-07/470780158384737.jpg","title":"手機上傳","description":""},{"file":"2022-07/470780198384733.jpg","title":"手機上傳","description":""}]},{"ts":1657707412,"title":"江明宗新增了 4 張相片。","text":"下午參與 江品璁  的街講， 江國銘  、 台南政治實習菜鳥  也一起支援，三江持續在街頭訴說理念！台南面臨許多問題，有高房價、低薪與停車空間不足等等，請大家支持 台灣民眾黨  的我們走入議會，讓台南改變成真！\n\n#北中西區台南市議員參選人江明宗","external":[],"images":[{"file":"2022-07/470289428433810.jpg","title":"手機上傳","description":""},{"file":"2022-07/470289468433806.jpg","title":"手機上傳","description":""},{"file":"2022-07/470289521767134.jpg","title":"手機上傳","description":""},{"file":"2022-07/470289571767129.jpg","title":"手機上傳","description":""}]},{"ts":1657672790,"title":"江明宗新增了 4 張相片。","text":"早安！早上來到中西區街講，感謝 江國銘  、 台南政治實習菜鳥 支援， #步行城市 的理念希望可以帶動台南經濟發展，同時改善台南的交通問題，台南交通事故死傷對比人口比率多年來都是全國最高，年底選舉請支持 台灣民眾黨  的我們，讓我們進入市議會好好監督市政府！\n\n#小額捐款支持明宗 https://kiang.oen.tw\n#北中西區台南市議員參選人江明宗","external":[],"images":[{"file":"2022-07/469955418467211.jpg","title":"手機上傳","description":""},{"file":"2022-07/469955458467207.jpg","title":"手機上傳","description":""},{"file":"2022-07/469955488467204.jpg","title":"手機上傳","description":""},{"file":"2022-07/469955535133866.jpg","title":"手機上傳","description":""}]},{"ts":1657624995,"title":"江明宗新增了 1 張相片。","text":"跟著 江品璁 、 江國銘 、 台南政治實習菜鳥  一起參與捷運說明會，沒辦法前來的朋友可以參考簡報與交通局直播\n\n簡報檔案\nhttps://www.rapid-transit.org/tainanmrt/storage/uploads/612365b4b2d83nL.pdf\n\n#北中西區台南市議員參選人江明宗","external":[],"images":[{"file":"2022-07/469488008513952.jpg","title":"手機上傳","description":"跟著 @[100065672431935:2048:江品璁] 、 @[100045208796770:2048:江國銘] 、 台南政治實習菜鳥  一起參與捷運說明會，沒辦法前來的朋友可以參考簡報與交通局直播\n\n簡報檔案\nhttps://www.rapid-transit.org/tainanmrt/storage/uploads/612365b4b2d83nL.pdf\n\n#北中西區台南市議員參選人江明宗"}]},{"ts":1657624720,"title":"江明宗新增了 1 張相片。","text":"參與 江國銘 在仁德的街講，還有 江品璁 、 台南政治實習菜鳥 同行，只是過程中遇到路口車禍發生，所以中斷街講去協助事故現場的疏導，在警方到場後才離開\n\n安全是回家唯一的路，希望大家小心駕駛！\n\n#北中西區台南市議員參選人江明宗","external":[],"images":[{"file":"2022-07/469485618514191.jpg","title":"手機上傳","description":"參與 @[100045208796770:2048:江國銘] 在仁德的街講，還有 @[100065672431935:2048:江品璁] 、 台南政治實習菜鳥 同行，只是過程中遇到路口車禍發生，所以中斷街講去協助事故現場的疏導，在警方到場後才離開\n\n安全是回家唯一的路，希望大家小心駕駛！\n\n#北中西區台南市議員參選人江明宗"}]},{"ts":1657600079,"title":"江明宗分享了 1 則貼文。","text":"星期四歡迎大家一起來！","external":[{"url":"","name":""}],"images":[]},{"ts":1657595869,"title":"江明宗更新了他的近況。","text":"台南終於開始關注衛星影像變異點，希望有效減少濫倒事件","external":[],"images":[]},{"ts":1657584993,"title":"江明宗新增了 4 張相片。","text":"早上來到仁德參與 江國銘  的街講， 台南政治實習菜鳥 也到場支援， 我們沒有花大錢、沒有抹黑，一步一腳印走入社區，持續宣傳我們的參選理念，爭取大家的支持，期待大家年底選舉可以支持 台灣民眾黨  的我們！\n\n#北中西區台南市議員參選人江明宗","external":[],"images":[{"file":"2022-07/469163268546426.jpg","title":"手機上傳","description":""},{"file":"2022-07/469163298546423.jpg","title":"手機上傳","description":""},{"file":"2022-07/469163335213086.jpg","title":"手機上傳","description":""},{"file":"2022-07/469163368546416.jpg","title":"手機上傳","description":""}]},{"ts":1657535697,"title":"江明宗新增了 4 張相片。","text":"下午來到台南公園街講，感謝 江國銘  、 江品璁  跟 台南政治實習菜鳥  的支援， #步行城市 的理念希望讓長輩走到街上、走入市場，台南執行友善騎樓政策超過 10 年，騎樓環境還是非常不友善，請支持 台灣民眾黨台南市黨部  的參選人走入議會，監督市政府，讓長輩們無論拄著拐杖、推著輪椅都可以好好走在路上！\n\n#小額捐款支持明宗 https://kiang.oen.tw\n#北中西區台南市議員參選人江明宗","external":[],"images":[{"file":"2022-07/468721198590633.jpg","title":"手機上傳","description":""},{"file":"2022-07/468721235257296.jpg","title":"手機上傳","description":""},{"file":"2022-07/468721278590625.jpg","title":"手機上傳","description":""},{"file":"2022-07/468721335257286.jpg","title":"手機上傳","description":""}]},{"ts":1657523165,"title":"江明宗新增了 1 張相片。","text":"恭喜 高虹安  委員通過 台灣民眾黨  提名，正式參選新竹市長，期待能夠讓新竹大步躍進！\n\n#北中西區台南市議員參選人江明宗","external":[],"images":[{"file":"2022-07/2141571772682941.jpg","title":"手機上傳","description":"恭喜 @[100044992518779:2048:高虹安]  委員通過 @[100044175652155:2048:台灣民眾黨]  提名，正式參選新竹市長，期待能夠讓新竹大步躍進！\n\n#北中西區台南市議員參選人江明宗"}]},{"ts":1657502307,"title":"江明宗新增了 4 張相片。","text":"早上來到北區街講， 江國銘 與 台南政治實習菜鳥 一起前來支援，我還是持續強調 #步行城市 對台南的重要性，希望市民朋友年底選舉支持 台灣民眾黨 的我們，我們會在市議會確實監督市政， #永續台灣世代共行 ！\n\n#小額捐款支持明宗 https://kiang.oen.tw\n#北中西區台南市議員參選人江明宗","external":[],"images":[{"file":"2022-07/2141406862699432.jpg","title":"手機上傳","description":""},{"file":"2022-07/2141406892699429.jpg","title":"手機上傳","description":""},{"file":"2022-07/2141406946032757.jpg","title":"手機上傳","description":""},{"file":"2022-07/2141406982699420.jpg","title":"手機上傳","description":""}]},{"ts":1657414795,"title":"江明宗更新了他的近況。","text":"兩天行程後，最大進展就是體重計數字！","external":[],"images":[]},{"ts":1657375095,"title":"江明宗新增了 1 張相片。","text":"台灣民眾黨   #全台大眾走 台南行腳今晚來到北區， 柯文哲  主席、 蔡壁如 與 邱臣遠 委員帶著大家走進花園夜市，沿途熱情要求合照的民眾絡繹不絕，夜市管委會也熱情提供餐點給我們，非常感謝大家的支持！\n\n民眾黨共同政見 #財政紀律 請大家支持，台北市的典範已經成為全國焦點，年底選舉我們要將這個典範帶來台南，打造負責的政治文化！\n\n#北中西區台南市議員參選人江明宗","external":[],"images":[{"file":"2022-07/2140216062818512.jpg","title":"手機上傳","description":"@[100044175652155:2048:台灣民眾黨]   #全台大眾走 台南行腳今晚來到北區， @[100044470088043:2048:柯文哲]  主席、 @[100044501493553:2048:蔡壁如] 與 @[100058177235239:2048:邱臣遠] 委員帶著大家走進花園夜市，沿途熱情要求合照的民眾絡繹不絕，夜市管委會也熱情提供餐點給我們，非常感謝大家的支持！\n\n民眾黨共同政見 #財政紀律 請大家支持，台北市的典範已經成為全國焦點，年底選舉我們要將這個典範帶來台南，打造負責的政治文化！\n\n#北中西區台南市議員參選人江明宗"}]},{"ts":1657370086,"title":"江明宗新增了 1 張相片。","text":"感謝 台南政治實習菜鳥 與許多志工朋友今晚的協助，我們下一站前往 #永大夜市 找 江品璁 ！\n\n#北中西區台南市議員參選人江明宗","external":[],"images":[{"file":"2022-07/2140162569490528.jpg","title":"手機上傳","description":"感謝 台南政治實習菜鳥 與許多志工朋友今晚的協助，我們下一站前往 #永大夜市 找 @[100065672431935:2048:江品璁] ！\n\n#北中西區台南市議員參選人江明宗"}]},{"ts":1657361887,"title":"江明宗新增了 1 張相片。","text":"稍晚 柯文哲 市長會跟我們一起逛花園夜市，遇到我們歡迎來打聲招呼！\n\n#北中西區台南市議員參選人江明宗","external":[],"images":[{"file":"2022-07/2140083566165095.jpg","title":"手機上傳","description":"稍晚 @[100044470088043:2048:柯文哲] 市長會跟我們一起逛花園夜市，遇到我們歡迎來打聲招呼！\n\n#北中西區台南市議員參選人江明宗"}]},{"ts":1657285117,"title":"江明宗新增了 1 張相片。","text":"台灣民眾黨   #全台大眾走 台南第五站來到東區，由 蔡宛秦。政治 x 三寶媽 帶大家感受大東夜市的越夜越美麗， 邱臣遠 委員跟民眾熱情互動讓大眾走隊伍歡笑聲不斷。\n\n民眾黨共同政見 #居住正義 請大家支持，解決囤房問題要靠民眾黨在中央與地方協力，給年輕人住得起的未來！\n\n#北中西區台南市議員參選人江明宗","external":[],"images":[{"file":"2022-07/2139326622907456.jpg","title":"手機上傳","description":"@[100044175652155:2048:台灣民眾黨]   #全台大眾走 台南第五站來到東區，由 @[100076508202653:2048:蔡宛秦。政治 x 三寶媽] 帶大家感受大東夜市的越夜越美麗， @[100058177235239:2048:邱臣遠] 委員跟民眾熱情互動讓大眾走隊伍歡笑聲不斷。\n\n民眾黨共同政見 #居住正義 請大家支持，解決囤房問題要靠民眾黨在中央與地方協力，給年輕人住得起的未來！\n\n#北中西區台南市議員參選人江明宗"}]},{"ts":1657274174,"title":"江明宗新增了 1 張相片。","text":"台灣民眾黨   #全台大眾走 台南第四站來到歸仁區，由 江國銘  帶大家穿越在黃昏市場中， #基隆劉德華 邱臣遠 委員與 #台南劉德華 炒熱了在地人採買的氣氛！\n\n民眾黨共同政見 #社會安全 請大家支持，讓社會溫情一棒接一棒，讓愛永不止息！\n\n#北中西區台南市議員參選人江明宗","external":[],"images":[{"file":"2022-07/2139211902918928.jpg","title":"手機上傳","description":"@[100044175652155:2048:台灣民眾黨]   #全台大眾走 台南第四站來到歸仁區，由 @[100045208796770:2048:江國銘]  帶大家穿越在黃昏市場中， #基隆劉德華 @[100058177235239:2048:邱臣遠] 委員與 #台南劉德華 炒熱了在地人採買的氣氛！\n\n民眾黨共同政見 #社會安全 請大家支持，讓社會溫情一棒接一棒，讓愛永不止息！\n\n#北中西區台南市議員參選人江明宗"}]},{"ts":1657264133,"title":"江明宗更新了他的近況。","text":"祝福安倍平安脫險","external":[],"images":[]},{"ts":1657253283,"title":"江明宗新增了 1 張相片。","text":"台灣民眾黨  #全台大眾走 台南第三站來到中西區，由 #江明宗 帶大家走入知名的水仙宮市場，在 邱臣遠 委員領軍下帶出了台南人的熱情相迎\n\n民眾黨共同政見 #經濟繁榮 請大家支持，共同發展台灣、共享經濟成果，推進台灣整體發展！\n\n#北中西區台南市議員參選人江明宗","external":[],"images":[{"file":"2022-07/2139013489605436.jpg","title":"手機上傳","description":"@[100044175652155:2048:台灣民眾黨]  #全台大眾走 台南第三站來到中西區，由 #江明宗 帶大家走入知名的水仙宮市場，在 @[100058177235239:2048:邱臣遠] 委員領軍下帶出了台南人的熱情相迎\n\n民眾黨共同政見 #經濟繁榮 請大家支持，共同發展台灣、共享經濟成果，推進台灣整體發展！\n\n#北中西區台南市議員參選人江明宗"}]},{"ts":1657247999,"title":"江明宗新增了 1 張相片。","text":"今天行程要進入走唱階段","external":[],"images":[{"file":"2022-07/2138961539610631.jpg","title":"手機上傳","description":"今天行程要進入走唱階段"}]},{"ts":1657246006,"title":"江明宗新增了 1 張相片。","text":"台灣民眾黨 #全台大眾走 台南第二站來到安南區， 陳詩薇 市議員參選人/安南區 帶我們走進最著名的果菜批發市場，體驗台南的物產豐饒\n\n邱臣遠 委員從北部帶隊南下參與，帶隊宣傳民眾黨共同政見 #永續環境 ，請大家支持，讓我們共同打造更好的台南、更好的台灣！\n\n#北中西區台南市議員參選人江明宗","external":[],"images":[{"file":"2022-07/2138944072945711.jpg","title":"手機上傳","description":"@[100044175652155:2048:台灣民眾黨] #全台大眾走 台南第二站來到安南區， @[100076077235082:2048:陳詩薇 市議員參選人/安南區] 帶我們走進最著名的果菜批發市場，體驗台南的物產豐饒\n\n@[100058177235239:2048:邱臣遠] 委員從北部帶隊南下參與，帶隊宣傳民眾黨共同政見 #永續環境 ，請大家支持，讓我們共同打造更好的台南、更好的台灣！\n\n#北中西區台南市議員參選人江明宗"}]},{"ts":1657242723,"title":"江明宗新增了 1 張相片。","text":"今天其實改行兜售斗笠\n\n#全台大眾走","external":[],"images":[{"file":"2022-07/2138905052949613.jpg","title":"手機上傳","description":"今天其實改行兜售斗笠\n\n#全台大眾走"}]},{"ts":1657242368,"title":"江明宗新增了 3 張相片。","text":"台灣民眾黨 #全台大眾走 台南的第一站我們來到善化， 洪岳銘 是在地青農，透過專業代耕服務在地；我們這次選舉的共同政見是 『永續台灣、世代共行』，除了拜託大家支持在地的參選人，也請大家一定要幫忙完成 18歲公民權公投的複決，讓更多年輕人可以共同決定台灣未來發展！\n\n#北中西區台南市議員參選人江明宗","external":[],"images":[{"file":"2022-07/2138901369616648.jpg","title":"手機上傳","description":""},{"file":"2022-07/2138901409616644.jpg","title":"手機上傳","description":""},{"file":"2022-07/2138901462949972.jpg","title":"手機上傳","description":""}]},{"ts":1657236075,"title":"江明宗新增了 1 張相片。","text":"這斗笠怎麼感覺特別重？","external":[],"images":[{"file":"2022-07/2138850702955048.jpg","title":"手機上傳","description":"這斗笠怎麼感覺特別重？"}]},{"ts":1657189357,"title":"江明宗新增了 4 張相片。","text":"下午在永康參與 江品璁  的街講，同行的還有 江國銘  與 台南政治實習菜鳥  ，我們一起在路口探討台南面臨的問題，希望大家年底選舉可以把票投給我們，讓我們進入議會解決大家的問題！\n\n#北中西區台南市議員參選人江明宗","external":[],"images":[{"file":"2022-07/2138380203002098.jpg","title":"手機上傳","description":""},{"file":"2022-07/2138380253002093.jpg","title":"手機上傳","description":""},{"file":"2022-07/2138380289668756.jpg","title":"手機上傳","description":""},{"file":"2022-07/2138380323002086.jpg","title":"手機上傳","description":""}]},{"ts":1657155869,"title":"江明宗新增了 1 張相片。","text":"早安，早上來到北區與永康交界處進行街講，感謝 江國銘 與 台南政治實習菜鳥  前來支援。我持續在陳述 #步行城市 理念，希望孩子可以用步行的方式走到學校，台南執行多年的通學步道政策，往往只能讓孩子繞行學校一圈，江明宗進入議會要好好監督市府改進，讓孩子真的可以從家裡走到學校，讓孩子可以有一個安全的步行環境！\n\n#小額捐款支持明宗 https://kiang.oen.tw\n#北中西區台南市議員參選人江明宗","external":[],"images":[{"file":"2022-07/2138117819695003.jpg","title":"手機上傳","description":"早安，早上來到北區與永康交界處進行街講，感謝 @[100045208796770:2048:江國銘] 與 台南政治實習菜鳥  前來支援。我持續在陳述 #步行城市 理念，希望孩子可以用步行的方式走到學校，台南執行多年的通學步道政策，往往只能讓孩子繞行學校一圈，江明宗進入議會要好好監督市府改進，讓孩子真的可以從家裡走到學校，讓孩子可以有一個安全的步行環境！\n\n#小額捐款支持明宗 https://kiang.oen.tw\n#北中西區台南市議員參選人江明宗"}]},{"ts":1657100853,"title":"江明宗新增了 1 張相片。","text":"台灣民眾黨 的 #全台大眾走 活動在這週五 (7/8) 、六 (7/9) 要進入台南，我們要一起走上街頭宣揚「永續台灣、世代共行」的理念，我們要挺 18 歲公民權！\n\n歡迎大家一起參與，一步一腳印去帶出台南的新想像！\n\n柯文哲 謝立功  蔡壁如 台灣民眾黨台南市黨部 洪岳銘 陳詩薇 市議員參選人/安南區 江國銘 蔡宛秦。政治 x 三寶媽  江品璁 \n\n#北中西區台南市議員參選人江明宗","external":[],"images":[{"file":"2022-07/2137623763077742.jpg","title":"手機上傳","description":"@[100044175652155:2048:台灣民眾黨] 的 #全台大眾走 活動在這週五 (7/8) 、六 (7/9) 要進入台南，我們要一起走上街頭宣揚「永續台灣、世代共行」的理念，我們要挺 18 歲公民權！\n\n歡迎大家一起參與，一步一腳印去帶出台南的新想像！\n\n@[100044470088043:2048:柯文哲] @[100050648012240:2048:謝立功]  @[100044501493553:2048:蔡壁如] @[100068850324817:2048:台灣民眾黨台南市黨部] @[100077302973805:2048:洪岳銘] @[100076077235082:2048:陳詩薇 市議員參選人/安南區] @[639492706119168:274:江國銘] @[104501285433963:274:蔡宛秦。政治 x 三寶媽]  @[100065672431935:2048:江品璁] \n\n#北中西區台南市議員參選人江明宗"}]},{"ts":1657062926,"title":"江明宗新增了 1 張相片。","text":"早安，早上來到歸仁 86 高架橋下跟 江國銘 在路口宣講，新豐區需要更多地方創生的促成，希望大家支持在地的 台灣民眾黨 參選人！\n\n#北中西區台南市議員參選人江明宗","external":[],"images":[{"file":"2022-07/2137319423108176.jpg","title":"手機上傳","description":"早安，早上來到歸仁 86 高架橋下跟 @[100045208796770:2048:江國銘] 在路口宣講，新豐區需要更多地方創生的促成，希望大家支持在地的 @[100044175652155:2048:台灣民眾黨] 參選人！\n\n#北中西區台南市議員參選人江明宗"}]},{"ts":1657031637,"title":"江明宗更新了他的近況。","text":"高職夜間部、夜二專、夜二技，我是 #類大學畢業生 ，百分百不會有論文抄襲問題","external":[],"images":[]},{"ts":1657018925,"title":"江明宗新增了 4 張相片。","text":"下午來到仁德參與 江國銘 的街講，同行的還有 江品璁 與 台南政治實習菜鳥  ，我們在街頭宣揚參選理念，不是政二代、富二代，希望用一步一腳印的精神爭取大家支持！\n\n#北中西區台南市議員參選人江明宗","external":[],"images":[{"file":"2022-07/2136930909813694.jpg","title":"手機上傳","description":""},{"file":"2022-07/2136930953147023.jpg","title":"手機上傳","description":""},{"file":"2022-07/2136930996480352.jpg","title":"手機上傳","description":""},{"file":"2022-07/2136931079813677.jpg","title":"手機上傳","description":""}]},{"ts":1656933555,"title":"江明宗新增了 4 張相片。","text":"下午在北區街講、掃街， 江國銘 、 江品璁 跟三位實習生一起參與，我們走在街頭訴說理念，希望大家年底可以支持我們，支持 台灣民眾黨 的參選人！\n\n#小額捐款支持明宗 https://kiang.oen.tw\n#北中西區台南市議員參選人江明宗","external":[],"images":[{"file":"2022-07/2136160046557447.jpg","title":"手機上傳","description":""},{"file":"2022-07/2136160093224109.jpg","title":"手機上傳","description":""},{"file":"2022-07/2136160126557439.jpg","title":"手機上傳","description":""},{"file":"2022-07/2136160319890753.jpg","title":"手機上傳","description":""}]},{"ts":1656911051,"title":"江明宗新增了 1 張相片。","text":"今天開始，來自 #台南大學 的三位實習生會一起參與選舉行程，願意走到第一線嘗試需要很大勇氣，希望遇到的朋友不吝加油打氣！也希望年底的選舉大家可以多多支持！\n\n#北中西區台南市議員參選人江明宗","external":[],"images":[{"file":"2022-07/2135977203242398.jpg","title":"手機上傳","description":"今天開始，來自 #台南大學 的三位實習生會一起參與選舉行程，願意走到第一線嘗試需要很大勇氣，希望遇到的朋友不吝加油打氣！也希望年底的選舉大家可以多多支持！\n\n#北中西區台南市議員參選人江明宗"}]},{"ts":1656889600,"title":"江明宗新增了 1 張相片。","text":"早安，早上跟 江國銘 來到仁德街講，希望大家支持！\n\n#北中西區台南市議員參選人江明宗","external":[],"images":[{"file":"2022-07/2135771809929604.jpg","title":"手機上傳","description":"早安，早上跟 @[100045208796770:2048:江國銘] 來到仁德街講，希望大家支持！\n\n#北中西區台南市議員參選人江明宗"}]},{"ts":1656886494,"title":"江明宗新增了 1 張相片。","text":"「囤房重稅、出租輕稅」就是民眾黨支持的房市問題解方，現有財政部公佈的數字並不足以呈現台灣房市的全貌，究竟一個家庭應該要擁有多少房子或每個人應該要擁有多少空間才夠？房子貸款或租金在什麼樣的水平才不會造成眼前所得水平的沈重負擔？以及租屋市場究竟有多少黑數？\n\n這些問題可以透過政府擁有的不同資料交叉比對來推估全貌，進而讓公共討論環繞著事實延伸，現在這樣擠牙膏的方式搭配網路操作風向，看不出執政黨解決居住正義問題的決心。蔡英文總統的房市三箭包含「改革房產稅制」、「健全租屋體系」、「建二十萬戶社宅」， 6 年過去了，你覺得實現了多少？\n\n#北中西區台南市議員參選人江明宗","external":[],"images":[{"file":"2022-07/2135736123266506.png","title":"相片","description":"「囤房重稅、出租輕稅」就是民眾黨支持的房市問題解方，現有財政部公佈的數字並不足以呈現台灣房市的全貌，究竟一個家庭應該要擁有多少房子或每個人應該要擁有多少空間才夠？房子貸款或租金在什麼樣的水平才不會造成眼前所得水平的沈重負擔？以及租屋市場究竟有多少黑數？\n\n這些問題可以透過政府擁有的不同資料交叉比對來推估全貌，進而讓公共討論環繞著事實延伸，現在這樣擠牙膏的方式搭配網路操作風向，看不出執政黨解決居住正義問題的決心。蔡英文總統的房市三箭包含「改革房產稅制」、「健全租屋體系」、「建二十萬戶社宅」， 6 年過去了，你覺得實現了多少？\n\n#北中西區台南市議員參選人江明宗"}]},{"ts":1656853204,"title":"江明宗更新了他的近況。","text":"在台灣擁有房子的人數 804 萬，以 2300 萬人口來說，大部分人是沒有自己房子的","external":[],"images":[]},{"ts":1656780104,"title":"江明宗新增了 1 張相片。","text":"台灣民眾黨 的議員參選人越來越多，要一個一個查閱大家的動態比較費時，所以寫了一個小網頁，一次看整個縣市所有議員參選人臉書動態，也提供給大家參考\n\nhttps://kiang.github.io/vote2022/tpp_fb.html\n\n只要在網頁最上方選擇縣市就可以展開該縣市議員參選人臉書，這是從選區地圖延伸而來，如果你喜歡在地圖上一個一個點也可以試試\n\n選區地圖 - https://kiang.github.io/vote2022/tpp.html\n\n#北中西區台南市議員參選人江明宗","external":[],"images":[{"file":"2022-07/2134814516692000.jpg","title":"相片","description":"@[100044175652155:2048:台灣民眾黨] 的議員參選人越來越多，要一個一個查閱大家的動態比較費時，所以寫了一個小網頁，一次看整個縣市所有議員參選人臉書動態，也提供給大家參考\n\nhttps://kiang.github.io/vote2022/tpp_fb.html\n\n只要在網頁最上方選擇縣市就可以展開該縣市議員參選人臉書，這是從選區地圖延伸而來，如果你喜歡在地圖上一個一個點也可以試試\n\n選區地圖 - https://kiang.github.io/vote2022/tpp.html\n\n#北中西區台南市議員參選人江明宗"}]},{"ts":1656670751,"title":"江明宗更新了他的近況。","text":"本土病例地圖下午因為疾管署資料錯誤跟著出錯，目前資料已經修正！","external":[],"images":[]},{"ts":1656652761,"title":"江明宗新增了 1 張相片。","text":"今天跟 #憲哥 一起走訪了安南區兩間廟宇，沿途探討宮廟與生活的連結，也在他的介紹中知道 #朝興宮 與 #朝皇宮 裡的一些藝術、文化典藏，與背後的故事。\n\n宮廟文化是台南的一個特色，我希望藉由更多的理解與交流來建立連接，進而有機會像日本京都一樣，讓宗教活動可以提昇到國際層次，也讓其中美好的部分可以持續傳承下去！\n\n#北中西區台南市議員參選人江明宗","external":[],"images":[{"file":"2022-07/2133682670138518.jpg","title":"手機上傳","description":"今天跟 #憲哥 一起走訪了安南區兩間廟宇，沿途探討宮廟與生活的連結，也在他的介紹中知道 #朝興宮 與 #朝皇宮 裡的一些藝術、文化典藏，與背後的故事。\n\n宮廟文化是台南的一個特色，我希望藉由更多的理解與交流來建立連接，進而有機會像日本京都一樣，讓宗教活動可以提昇到國際層次，也讓其中美好的部分可以持續傳承下去！\n\n#北中西區台南市議員參選人江明宗"}]}]